pyriodic_aflow/__init__.py
pyriodic_aflow/version.py
pyriodic_aflow/unit_cells/__init__.py
pyriodic_aflow/unit_cells/aflow_db.json
pyriodic_aflow-0.1.1.dist-info/LICENSE
pyriodic_aflow-0.1.1.dist-info/METADATA
pyriodic_aflow-0.1.1.dist-info/WHEEL
pyriodic_aflow-0.1.1.dist-info/entry_points.txt
pyriodic_aflow-0.1.1.dist-info/top_level.txt
pyriodic_aflow-0.1.1.dist-info/RECORD
