Metadata-Version: 2.1
Name: pyriodic-aflow
Version: 0.1.1
Summary: Pyriodic adapter to the AFLOW project crystal prototype database
Home-page: http://github.com/klarh/pyriodic-aflow
Author: Matthew Spellings
Author-email: matthew.p.spellings@gmail.com
License: GPL3
Project-URL: Documentation, http://pyriodic.readthedocs.io/
Project-URL: Source, https://github.com/klarh/pyriodic-aflow
Platform: UNKNOWN
Classifier: Development Status :: 3 - Alpha
Classifier: License :: OSI Approved :: GNU General Public License v3 (GPLv3)
Classifier: Programming Language :: Python :: 3
Requires-Python: >=3
Requires-Dist: pyriodic-structures
